<?xml version="1.0" encoding="utf-8"?>
<savedqueries xmlns:xsi="http://www.w3.org/2001/XMLSchema-instance">
  <savedquery>
    <IsCustomizable>1</IsCustomizable>
    <CanBeDeleted>0</CanBeDeleted>
    <isquickfindquery>0</isquickfindquery>
    <isprivate>0</isprivate>
    <isdefault>1</isdefault>
    <savedqueryid>{c7e9001e-442b-4657-9478-3142e531f54a}</savedqueryid>
    <layoutxml>
      <grid name="resultset" jump="ak_vehiclename" select="1" icon="1" preview="1">
        <row name="result" id="ak_vehicleid">
          <cell name="ak_vehiclename" width="300" />
          <cell name="ak_make" width="100" />
          <cell name="ak_model" width="100" />
          <cell name="ak_vehicleowneremail" width="154" />
        </row>
      </grid>
    </layoutxml>
    <querytype>0</querytype>
    <fetchxml>
      <fetch version="1.0" mapping="logical">
        <entity name="ak_vehicle">
          <attribute name="ak_vehicleid" />
          <attribute name="ak_vehiclename" />
          <order attribute="ak_vehiclename" descending="false" />
          <filter type="and">
            <condition attribute="statecode" operator="eq" value="0" />
          </filter>
          <attribute name="ak_make" />
          <attribute name="ak_model" />
          <attribute name="ak_vehicleowneremail" />
        </entity>
      </fetch>
    </fetchxml>
    <IntroducedVersion>1.0</IntroducedVersion>
    <LocalizedNames>
      <LocalizedName description="Active Vehicles" languagecode="1033" />
    </LocalizedNames>
  </savedquery>
</savedqueries>